Compiled from "RuntimeConstantPoolOOM.java"
public class com.fc.base.jvm.oom.RuntimeConstantPoolOOM {
  public com.fc.base.jvm.oom.RuntimeConstantPoolOOM();
    Code:
       0: aload_0
       1: invokespecial #1                  // Method java/lang/Object."<init>":()V
       4: return

  public static void main(java.lang.String[]);
    Code:
       0: ldc           #2                  // String a
       2: astore_1
       3: ldc           #3                  // String b
       5: astore_2
       6: aload_2
       7: astore_1
       8: ldc           #4                  // String c
      10: astore_2
      11: getstatic     #5                  // Field java/lang/System.out:Ljava/io/PrintStream;
      14: new           #6                  // class java/lang/StringBuilder
      17: dup
      18: invokespecial #7                  // Method java/lang/StringBuilder."<init>":()V
      21: ldc           #8                  // String a =
      23: invokevirtual #9                  // Method java/lang/StringBuilder.append:(Ljava/lang/String;)Ljava/lang/StringBuilder;
      26: aload_1
      27: invokevirtual #9                  // Method java/lang/StringBuilder.append:(Ljava/lang/String;)Ljava/lang/StringBuilder;
      30: invokevirtual #10                 // Method java/lang/StringBuilder.toString:()Ljava/lang/String;
      33: invokevirtual #11                 // Method java/io/PrintStream.println:(Ljava/lang/String;)V
      36: return
}
